confsecrets/__init__.py
confsecrets/cli.py
confsecrets/config.py
confsecrets/pbe.py
confsecrets/secrets.py
confsecrets/vault.py
confsecrets-0.0.4.dist-info/LICENSE
confsecrets-0.0.4.dist-info/METADATA
confsecrets-0.0.4.dist-info/WHEEL
confsecrets-0.0.4.dist-info/entry_points.txt
confsecrets-0.0.4.dist-info/top_level.txt
confsecrets-0.0.4.dist-info/RECORD
