Metadata-Version: 2.1
Name: confsecrets
Version: 0.0.4
Summary: Simple utility to symmetrically encrypt/decrypt application secrets
Home-page: https://github.com/danizen/confsecrets.git
Author: Dan Davis
Author-email: dan@danizen.net
Maintainer: Dan Davis
Maintainer-email: dan@danizen.net
License: UNKNOWN
Project-URL: Documentation, https://danizen.github.io/confsecrets/
Platform: UNKNOWN
Classifier: Development Status :: 4 - Beta
Classifier: License :: OSI Approved :: GNU General Public License v3 (GPLv3)
Classifier: Environment :: Web Environment
Classifier: Framework :: Django :: 1.11
Classifier: Framework :: Django :: 2.0
Classifier: Framework :: Django :: 2.1
Classifier: Framework :: Django :: 2.2
Classifier: Intended Audience :: Developers
Classifier: Intended Audience :: System Administrators
Classifier: Programming Language :: Python :: 3.6
Classifier: Programming Language :: Python :: 3.7
Classifier: Programming Language :: Python :: 3.8
Classifier: Topic :: Security :: Cryptography
Classifier: Topic :: Software Development
Classifier: Topic :: Utilities
Requires-Dist: cryptography
